snek_sploit/__init__.py
snek_sploit/lib/__init__.py
snek_sploit/lib/context.py
snek_sploit/lib/metasploit.py
snek_sploit/lib/rpc/__init__.py
snek_sploit/lib/rpc/auth.py
snek_sploit/lib/rpc/consoles.py
snek_sploit/lib/rpc/core.py
snek_sploit/lib/rpc/db.py
snek_sploit/lib/rpc/health.py
snek_sploit/lib/rpc/jobs.py
snek_sploit/lib/rpc/modules.py
snek_sploit/lib/rpc/plugins.py
snek_sploit/lib/rpc/sessions.py
snek_sploit/util/__init__.py
snek_sploit/util/constants.py
snek_sploit/util/enums.py
snek_sploit/util/exceptions.py
snek_sploit/util/retry.py
snek_sploit-0.8.6.dist-info/LICENSE
snek_sploit-0.8.6.dist-info/METADATA
snek_sploit-0.8.6.dist-info/WHEEL
snek_sploit-0.8.6.dist-info/RECORD
