Metadata-Version: 2.3
Name: snek-sploit
Version: 0.8.6
Summary: Python RPC client for Metasploit Framework
License: MIT
Keywords: metasploit,msf,rpc,client
Author: Jiří Rája
Author-email: jiri.raja@gmail.com
Maintainer: Jiří Rája
Maintainer-email: jiri.raja@gmail.com
Requires-Python: >=3.8,<4.0
Classifier: License :: OSI Approved :: MIT License
Classifier: Programming Language :: Python :: 3
Classifier: Programming Language :: Python :: 3.8
Classifier: Programming Language :: Python :: 3.9
Classifier: Programming Language :: Python :: 3.10
Classifier: Programming Language :: Python :: 3.11
Classifier: Programming Language :: Python :: 3.12
Classifier: Programming Language :: Python :: 3.13
Requires-Dist: msgpack (>=1.0.8,<2.0.0)
Requires-Dist: requests (>=2.31.0,<3.0.0)
Project-URL: Homepage, https://github.com/SadParad1se/snek-sploit
Project-URL: Repository, https://github.com/SadParad1se/snek-sploit
